Metadata-Version: 1.0
Name: ImgConverter
Version: 1.0.0
Summary: Pure Python Image conversion package
Home-page: https://github.com/mrstephenneal/ImgConverter
Author: Stephen Neal
Author-email: stephen@stephenneal.net
License: UNKNOWN
Platform: UNKNOWN
